<?xml version="1.0" encoding="utf-8" ?>
<c2eventsheet>
    <!--All the 'name' attributes are ignored by Construct 2 - they are there for readability only.-->
    <name>Main Screen Events</name>
    <events>
        <event-group description="" sid="7837759549000638" title="Main Events for Game" />
        <comment>Configuration </comment>
        <include>Game Configuration</include>
        <comment>Code to tidy up and reset frame</comment>
        <include>Maze Construction</include>
        <comment>General code for moving objects</comment>
        <include>MovingObjects</include>
        <comment>Code which controls the game</comment>
        <include>Game Controller</include>
        <comment>Joypad events</comment>
        <include>Joystick Controller</include>
        <comment>Quiz is displayed</comment>
        <include>QuizSection</include>
        <comment>Versions of game - configuration functions</comment>
        <include>All_Configurations</include>
    </events>
</c2eventsheet>
